<f id="Top02_70SWOscardressCutOut" parentId="Top02">
  <g id="Top">
    <s id="Top02_70_torso_f" cId="Torso" s="items/base/consumables/clothing/top02/top02_70_torso.png" pri="0.8"/>
    <c sId="Top02_70_torso_f" c="5843379" a="0.70" b="41.5" ct="0.68" lId="Top02_70Color1" lw="N"/>
      <s id="Top02_56Skin" cId="Torso" s="items/base/consumables/clothing/top02/top02_skin_66.png" pri="0.5"/>
      <c sId="Top02_56Skin" c="16760213" a="0.29" b="11.7" ct="0.33" lId="SkinColor" lw="N"/>
  </g>
  <g id="Legs" icon="items/base/consumables/clothing/top02/top02_24_icon_piratedress.png">
    <s id="Top02_leg_62IdleBase" cId="LegIdle" s="items/base/consumables/clothing/top02/bot02_70_idle_base.png" pri="4.1"/>
    <c sId="Top02_leg_62IdleBase" c="5843379" a="0.70" b="41.5" ct="0.68" lId="Top02_70Color1" lw="N"/>
    <s id="Top02_leg_62Walk1Base" cId="LegWalk1" s="items/base/consumables/clothing/top02/bot02_70_walk1_base.png" pri="4.1"/>
    <c sId="Top02_leg_62Walk1Base" c="5843379" a="0.70" b="41.5" ct="0.68" lId="Top02_70Color1" lw="N"/>
    <s id="Top02_leg_62Walk2Base" cId="LegWalk2" s="items/base/consumables/clothing/top02/bot02_70_walk2_base.png" pri="4.1"/>
    <c sId="Top02_leg_62Walk2Base" c="5843379" a="0.70" b="41.5" ct="0.68" lId="Top02_70Color1" lw="N"/>
    <s id="Top02_leg_62Walk3Base" cId="LegWalk3" s="items/base/consumables/clothing/top02/bot02_70_walk3_base.png" pri="4.1"/>
    <c sId="Top02_leg_62Walk3Base" c="5843379" a="0.70" b="41.5" ct="0.68" lId="Top02_70Color1" lw="N"/>
    <s id="Top02_leg_62Walk4Base" cId="LegWalk4" s="items/base/consumables/clothing/top02/bot02_70_walk4_base.png" pri="4.1"/>
    <c sId="Top02_leg_62Walk4Base" c="5843379" a="0.70" b="41.5" ct="0.68" lId="Top02_70Color1" lw="N"/>
    <s id="Top02_leg_62SitUpperBase" cId="LegSitUpper" s="items/base/consumables/clothing/top02/bot02_70_sit_base.png" pri="4.1"/>
    <c sId="Top02_leg_62SitUpperBase" c="5843379" a="0.70" b="41.5" ct="0.68" lId="Top02_70Color1" lw="N"/>
  </g>
  <g id="Sleeve" name="Sleeve" icon="$bm/icon_m_tshirt.png">
    <s id="Top02_70ArmIdleBase" cId="ArmIdle" s="items/base/consumables/clothing/top02/top02_70_idle.png" pri="0.8"/>
    <s id="Top02_70ArmWalk1Base" cId="ArmWalk1" s="items/base/consumables/clothing/top02/top02_70_walk1.png" pri="0.8"/>
    <s id="Top02_70ArmWalk2Base" cId="ArmWalk2" s="items/base/consumables/clothing/top02/top02_70_walk2.png" pri="0.8"/>
    <s id="Top02_70ArmWalk3Base" cId="ArmWalk3" s="items/base/consumables/clothing/top02/top02_70_walk3.png" pri="0.8"/>
    <s id="Top02_70ArmSitBase" cId="ArmSit" s="items/base/consumables/clothing/top02/top02_70_sit.png" pri="0.8"/>
    <s id="Top02_70ArmThrowBase" cId="ArmThrow" s="items/base/consumables/clothing/top02/top02_70_throw.png" pri="0.8"/>
    <s id="Top02_70ArmRaiseBase" cId="ArmRaise" s="items/base/consumables/clothing/top02/top02_70_raise.png" pri="0.8"/>
    <c sId="Top02_70ArmIdleBase" c="5843379" a="0.70" b="41.5" ct="0.68" lId="Top02_70Color1" lw="N"/>
    <c sId="Top02_70ArmWalk1Base" c="5843379" a="0.70" b="41.5" ct="0.68" lId="Top02_70Color1" lw="N"/>
    <c sId="Top02_70ArmWalk2Base" c="5843379" a="0.70" b="41.5" ct="0.68" lId="Top02_70Color1" lw="N"/>
    <c sId="Top02_70ArmWalk3Base" c="5843379" a="0.70" b="41.5" ct="0.68" lId="Top02_70Color1" lw="N"/>
    <c sId="Top02_70ArmSitBase" c="5843379" a="0.70" b="41.5" ct="0.68" lId="Top02_70Color1" lw="N"/>
    <c sId="Top02_70ArmThrowBase" c="5843379" a="0.70" b="41.5" ct="0.68" lId="Top02_70Color1" lw="N"/>
    <c sId="Top02_70ArmRaiseBase" c="5843379" a="0.70" b="41.5" ct="0.68" lId="Top02_70Color1" lw="N"/>
  </g>
  <g id="Icon">
    <t id="IconTop02_70" icon="items/base/consumables/clothing/top02/top02_70_icon_swoscardresscutout_a.png" w="48" h="48"/>
    <s id="IconTop02_70Base" cId="IconTop02_70" s="items/base/consumables/clothing/top02/top02_70_icon_swoscardresscutout_1.png" pri="1"/>
    <c sId="IconTop02_70Base" c="5843379" a="0.70" b="41.5" ct="0.68" lId="Top02_70Color1" lw="N"/>
  </g>
  <g id="FragmentUI">
    <b id="Top02_70Color1" name="Color 1" desc="Choose a color" sel="Purple" seld="Blue">
      <c id="White" icon="$bu/icon_white.png" c="10592673" a="0.49" b="64.5" ct="1.01" lId="Top02_70Color1"/>
      <c id="Grey" icon="$bu/icon_grey.png" c="7895160" a="0.99" b="43.1" ct="1.76" lId="Top02_70Color1"/>
      <c id="Lilac" icon="$bu/icon_lilac.png" c="16751599" a="0.69" b="30.9" ct="1.21" lId="Top02_70Color1"/>
      <c id="LightPink" icon="$bu/icon_lightpink.png" c="16231623" a="0.79" b="43.1" ct="1.48" lId="Top02_70Color1"/>
      <c id="Pink" icon="$bu/icon_pink.png" c="16216719" a="0.90" b="70.6" ct="1.17" lId="Top02_70Color1"/>
      <c id="Red" icon="$bu/icon_red.png" c="10422528" a="0.87" b="60.9" ct="1.23" lId="Top02_70Color1"/>
      <c id="Orange" icon="$bu/icon_orange.png" c="16221202" a="1.00" b="69.0" ct="1.21" lId="Top02_70Color1"/>
      <c id="Yellow" icon="$bu/icon_yellow.png" c="16776960" a="0.97" b="39.5" ct="1.04" lId="Top02_70Color1"/>
      <c id="Green" icon="$bu/icon_green.png" c="908049" a="0.81" b="19.2" ct="0.56" lId="Top02_70Color1"/>
      <c id="GreenDark" icon="$bu/icon_greendark.png" c="878364" a="0.83" b="49.5" ct="1.70" lId="Top02_70Color1"/>
      <c id="Indigo" icon="$bu/icon_indigo.png" c="1561765" a="0.58" b="22.5" ct="1.09" lId="Top02_70Color1"/>
      <c id="BlueGreen" icon="$bu/icon_bluegreen.png" c="2851707" a="0.76" b="38.3" ct="1.06" lId="Top02_70Color1"/>
      <c id="LightBlue" name="Stone wash" icon="$bu/icon_stonewash.png" c="7774670" a="0.84" b="47.9" ct="0.91" lId="Top02_70Color1"/>
      <c id="Blue" icon="$bu/icon_blue.png" c="2858731" a="0.74" b="33.7" ct="1.03" lId="Top02_70Color1"/>
      <c id="NavyBlue" icon="$bu/icon_medblue.png" c="2820471" a="0.50" b="12.6" ct="1.21" lId="Top02_70Color1"/>
      <c id="Purple" icon="$bu/icon_purple.png" c="5843379" a="0.70" b="41.5" ct="0.68" lId="Top02_70Color1"/>
      <c id="Kaki" icon="$bu/icon_kaki.png" c="11769952" a="0.82" b="28.9" ct="1.09" lId="Top02_70Color1"/>
      <c id="Olive" icon="$bu/icon_olive.png" c="3950097" a="0.86" b="68.6" ct="2.00" lId="Top02_70Color1"/>
      <c id="Brown" icon="$bu/icon_brown.png" c="4534275" a="0.84" b="60.5" ct="2.00" lId="Top02_70Color1"/>
      <c id="Burgandy" icon="$bu/icon_burgandy.png" c="5570560" a="0.69" b="39.9" ct="1.39" lId="Top02_70Color1"/>
      <c id="Black" icon="$bu/icon_black.png" c="5395026" a="0.88" b="41.7" ct="1.95" lId="Top02_70Color1"/>
    </b>
    <wizbox id="UI" uiInitScript="width=320; height=100; setStyle('horizontalGap', 4);" dir="H">
      <wizchoice id="Color1" name="Color 1" uiClassName="com.smallworlds.start.intro.avatar.ui.AvatarComboChoiceUI" bId="Top02_70Color1"/>
    </wizbox>
  </g>
  <ds id="JSTop"/>
  <ds id="Bot03"/>
  <ds id="JSBottom"/>
</f>