<item.SpriteItem id="6927" name="Manga Cavada Listrada Rock" desc="Uma camiseta listrada sem mangas" tags="rare,consumable,clothing,actionbar,wear,top01,action_wearable_toggle" icon="items/base/consumables/clothing/top01/top01_165_icon_singlet_a.png" price="510" minLevel="1" minCPLevel="1" dropTargetType="none" dropTargetList="floor,table,avatar" dropTargetClamp="none">
  <volume>
    <box min="-0.34,0,-0.25" max="0.34,0.1,0.25"/>
  </volume>
  <events>
    <event id="manipulate" script="scripts/item/manipulate.as"/>
    <event id="action" script="scripts/item/action_wearable.as"/>
    <event id="action_inventory" script="scripts/item/action_inventory_wearable.as"/>
    <event id="action_try" script="scripts/item/action_wearable_try.as"/>
    <event id="select_inventory" script="scripts/item/select_inventory_wearable.as"/>
    <event id="select" script="scripts/item/select_wearable.as"/>
  </events>
  <data>
    <entry key="hasAccessSecurity" value="false"/>
    <entry key="fragmentURL" value="items/base/consumables/clothing/top01/top01_165_frag_stripesinglet.xml"/>
    <entry key="fragmentUIGroup" value="FragmentUI"/>
    <entry key="fragmentUIID" value="UI"/>
  </data>
  <textures>
    <texture id="clothes" source="items/base/consumables/clothing/top01/top01_165_item_stripesinglet.png" cols="2" rows="1"/>
  </textures>
  <nodes>
    <node id="Node">
      <box min="-0.34,0,-0.25" max="0.34,0.1,0.25"/>
      <layers>
        <layer id="Layer" texture="clothes">
          <view angle="45" x="2" y="21"/>
          <view angle="135" x="-2" y="21" hm="true"/>
          <view angle="225" col="1" x="-1" y="19"/>
          <view angle="315" col="1" x="1" y="19" hm="true"/>
        </layer>
      </layers>
      <frames/>
      <animations/>
    </node>
  </nodes>
</item.SpriteItem>