<item.SpriteItem id="7465" name="Ãrvore Congelada" desc="Um pinheiro congelado [16 of 25]" tags="rare,misc" icon="items/base/consumables/clothing/accessory/acc_940_janbox_16_icon.png" price="250" minLevel="1" minCPLevel="1" dropTargetType="none" dropTargetList="floor,avatar" dropTargetClamp="none">
  <volume>
    <box min="-0.49,0,-0.49" max="0.49,3.2,0.49"/>
  </volume>
  <events>
    <event id="manipulate" script="scripts/item/manipulate.as"/>
    <event id="select" script="scripts/item/select.as"/>
  </events>
  <textures>
    <texture id="Texture" source="items/base/consumables/clothing/accessory/acc_940_janbox_16_item.png" cols="1" rows="1"/>
  </textures>
  <nodes>
    <node id="Node">
      <box min="-0.49,0,-0.49" max="0.49,3.2,0.49"/>
      <layers>
        <layer id="Layer" texture="Texture" y="12">
          <view angle="45" y="4"/>
          <view angle="135" x="4" y="4" hm="true"/>
          <view angle="225" y="4"/>
          <view angle="315" x="4" y="4" hm="true"/>
        </layer>
      </layers>
      <frames/>
      <animations/>
    </node>
  </nodes>
</item.SpriteItem>