<item.SpriteItem id="0" name="Christian the Chihuahua" desc="A Chihuahua head" dropTargetType="none" dropTargetList="floor, table,avatar" dropTargetClamp="none" entity="false">
  <volume>
    <box min="-0.3,0,-0.3" max="0.3,0.5,0.3"/>
  </volume>
  <events>
    <event id="manipulate" script="scripts/item/manipulate.as"/>
    <event id="select" script="scripts/item/select.as"/>
  </events>
  <textures>
    <texture id="bunny" source="items/base/consumables/head/con_head_194_ridgelord.png" cols="5" rows="1"/>
  </textures>
  <nodes>
    <node id="Node">
      <box min="-0.3,0,-0.3" max="0.3,0.5,0.3"/>
      <layers>
        <layer id="bunny" texture="bunny">
          <view angle="0" col="2" x="-5" y="40" hm="true"/>
          <view angle="45" x="-7" y="42"/>
          <view angle="90" col="1" y="44"/>
          <view angle="135" x="6" y="42" hm="true"/>
          <view angle="180" col="2" x="4" y="40"/>
          <view angle="225" col="3" x="8" y="43"/>
          <view angle="270" col="4" y="52"/>
          <view angle="315" col="3" x="-8" y="43" hm="true"/>
        </layer>
      </layers>
      <frames>
        <frame id="blink">
          <layerref id="bunny"/>
        </frame>
        <frame id="normal">
          <layerref id="bunny"/>
        </frame>
      </frames>
      <animations>
        <animation id="Animation" framerate="4"/>
      </animations>
    </node>
  </nodes>
</item.SpriteItem>